autoparis/__init__.py
autoparis/detectron_predict.py
autoparis/dzi_writer.py
autoparis/extract_predict.py
autoparis/generate_sif_scores.py
autoparis/refine_detectron.py
autoparis-0.1.data/scripts/install_apx_dependencies.sh
autoparis-0.1.dist-info/LICENSE
autoparis-0.1.dist-info/METADATA
autoparis-0.1.dist-info/WHEEL
autoparis-0.1.dist-info/entry_points.txt
autoparis-0.1.dist-info/top_level.txt
autoparis-0.1.dist-info/RECORD
